DmxOscServer/DmxOscServer.py
DmxOscServer/Fixture.py
DmxOscServer/__init__.py
DmxOscServer-1.0.5.dist-info/METADATA
DmxOscServer-1.0.5.dist-info/WHEEL
DmxOscServer-1.0.5.dist-info/top_level.txt
DmxOscServer-1.0.5.dist-info/RECORD
