Metadata-Version: 2.1
Name: DmxOscServer
Version: 1.0.5
Summary: A Python Lib to create a DMX compatible OSC server with handlers
Home-page: https://dmxoscserver.readthedocs.io/en/latest/
Author: Miniontoby
Project-URL: Bug Reports, https://github.com/Miniontoby/DmxOscServer/issues
Project-URL: Source, https://github.com/Miniontoby/DmxOscServer
Keywords: dmx,osc,server
Requires-Python: >=3.5
Requires-Dist: python-osc
